pyflip/LICENSE.txt
pyflip/README.md
pyflip/__init__.py
pyflip/definitions.py
pyflip/setup.py
pyflip/bin/win_32/LICENSE.txt
pyflip/bin/win_32/cbc.exe
pyflip/docs/example_1.md
pyflip/docs/readme.md
pyflip/pyflip.egg-info/PKG-INFO
pyflip/pyflip.egg-info/SOURCES.txt
pyflip/pyflip.egg-info/dependency_links.txt
pyflip/pyflip.egg-info/top_level.txt
pyflip/src/expression.py
pyflip/src/file_io.py
pyflip/src/model.py
pyflip/src/parameter.py
pyflip/src/run.py
pyflip/src/solution.py
pyflip/src/solver.py
pyflip/src/util.py
pyflip/src/variable.py
pyflip/test/stress_test.py
pyflip/test/unit_test.py
pyflip-0.1.3.dist-info/LICENSE.txt
pyflip-0.1.3.dist-info/METADATA
pyflip-0.1.3.dist-info/WHEEL
pyflip-0.1.3.dist-info/top_level.txt
pyflip-0.1.3.dist-info/RECORD
