Metadata-Version: 2.1
Name: pyflip
Version: 0.1.3
Summary: A simple and modern library for Linear and Integer Programming in Python 3
Home-page: https://github.com/aphi/pyflip
Author: Antony Phillips
Author-email: antony.e.phillips@gmail.com
License: MIT
Keywords: linear integer mathematical optimisation
Platform: UNKNOWN
Classifier: Programming Language :: Python :: 3.6
Classifier: License :: OSI Approved :: MIT License
Classifier: Operating System :: OS Independent
Classifier: Topic :: Scientific/Engineering :: Mathematics
